{
  "type": "minecraft:chest",
  "pools": [
    {
      "rolls": 2,
      "entries": [
        {
          "type": "minecraft:item",
          "name": "minecraft:enchanted_book",
          "functions": [
            {
              "function": "minecraft:set_nbt",
              "tag": "{StoredEnchantments: [{id:\"elytraplus:wind_rider\",lvl:1s}]}"
            }
          ],
          "conditions": [
            {
              "condition": "minecraft:random_chance",
              "chance": 0.1
            }
          ]
        },
        {
          "type": "minecraft:item",
          "name": "minecraft:enchanted_book",
          "functions": [
            {
              "function": "minecraft:set_nbt",
              "tag": "{StoredEnchantments: [{id:\"elytraplus:hover\",lvl:1s}]}"
            }
          ],
          "conditions": [
            {
              "condition": "minecraft:random_chance",
              "chance": 0.1
            }
          ]
        },
        {
          "type": "minecraft:item",
          "name": "minecraft:enchanted_book",
          "functions": [
            {
              "function": "minecraft:set_nbt",
              "tag": "{StoredEnchantments: [{id:\"elytraplus:wind_rider\",lvl:2s}]}"
            }
          ],
          "conditions": [
            {
              "condition": "minecraft:random_chance",
              "chance": 0.1
            }
          ]
        },
        {
          "type": "minecraft:item",
          "name": "minecraft:enchanted_book",
          "functions": [
            {
              "function": "minecraft:set_nbt",
              "tag": "{StoredEnchantments: [{id:\"elytraplus:hover\",lvl:2s}]}"
            }
          ],
          "conditions": [
            {
              "condition": "minecraft:random_chance",
              "chance": 0.1
            }
          ]
        },
        {
          "type": "minecraft:item",
          "name": "minecraft:enchanted_book",
          "functions": [
            {
              "function": "minecraft:set_nbt",
              "tag": "{StoredEnchantments: [{id:\"elytraplus:wind_rider\",lvl:3s}]}"
            }
          ],
          "conditions": [
            {
              "condition": "minecraft:random_chance",
              "chance": 0.1
            }
          ]
        },
        {
          "type": "minecraft:item",
          "name": "minecraft:enchanted_book",
          "functions": [
            {
              "function": "minecraft:set_nbt",
              "tag": "{StoredEnchantments: [{id:\"elytraplus:hover\",lvl:3s}]}"
            }
          ],
          "conditions": [
            {
              "condition": "minecraft:random_chance",
              "chance": 0.1
            }
          ]
        }
      ]
    }
  ],
  "random_sequence": "minecraft:chests/end_city_treasure"
}
